README.md
setup.py
fastgp/__init__.py
fastgp.egg-info/PKG-INFO
fastgp.egg-info/SOURCES.txt
fastgp.egg-info/dependency_links.txt
fastgp.egg-info/requires.txt
fastgp.egg-info/top_level.txt
fastgp/algorithms/__init__.py
fastgp/algorithms/afpo.py
fastgp/algorithms/fast_evaluate.py
fastgp/logging/__init__.py
fastgp/logging/archive.py
fastgp/logging/reports.py
fastgp/parametrized/__init__.py
fastgp/parametrized/mutation.py
fastgp/parametrized/simple_parametrized_terminals.py
fastgp/utilities/__init__.py
fastgp/utilities/benchmark_problems.py
fastgp/utilities/metrics.py
fastgp/utilities/operators.py
fastgp/utilities/subset_selection.py
fastgp/utilities/symbreg.py