Metadata-Version: 1.2
Name: fastgp
Version: 0.1.0
Summary: Fast genetic programming.
Home-page: https://github.com/cfusting/fastgp
Author: Chris Fusting
Author-email: cfusting@gmail.com
License: GNU GPLv3
Keywords: evolution machine learning artificial intelligence
Platform: UNKNOWN
Classifier: Development Status :: 3 - Alpha
Classifier: Intended Audience :: Science/Research
Classifier: Topic :: Scientific/Engineering :: Artificial Intelligence
Classifier: License :: OSI Approved :: GNU General Public License v3 (GPLv3)
Classifier: Programming Language :: Python :: 3
Requires-Python: >=2.7
